qumas/LensmodelWrapper/__init__.py
qumas/LensmodelWrapper/automatic_modeling.py
qumas/LensmodelWrapper/coming_delete/modeling.py
qumas/LensmodelWrapper/coming_delete/modeling_old.py
qumas/LensmodelWrapper/coming_delete/old_automatic_modeling.py
qumas/LensmodelWrapper/lensmodel/__init__.py
qumas/LensmodelWrapper/lensmodel/lensmodel
qumas/LensmodelWrapper/lensmodel_handler.py
qumas/LensmodelWrapper/lensmodel_reader.py
qumas/LensmodelWrapper/lensmodel_result_handler.py
qumas/LensmodelWrapper/lensmodel_wrapper.py
qumas/LensmodelWrapper/mass_models.py
qumas/LensmodelWrapper/mcmc_lensmodel.py
qumas/LensmodelWrapper/models/2g.json
qumas/LensmodelWrapper/models/SIS.json
qumas/LensmodelWrapper/models/__init__.py
qumas/LensmodelWrapper/models/double_models.json
qumas/LensmodelWrapper/models/model_setup.json
qumas/LensmodelWrapper/models/models.json
qumas/LensmodelWrapper/models/quad_models.json
qumas/LensmodelWrapper/utils.py
qumas/MicrolensingAnalysis/Update.py
qumas/MicrolensingAnalysis/WindowAnalysis.py
qumas/MicrolensingAnalysis/__init__.py
qumas/MicrolensingAnalysis/functions.py
qumas/MicrolensingAnalysis/microlensing_mag_plot.py
qumas/MicrolensingAnalysis/ratio_cont_core.py
qumas/MicrolensingAnalysis/rest_frame_windows/rest_frame_windows.csv
qumas/MicrolensingAnalysis/rest_frame_windows/rest_frame_windows.json
qumas/MicrolensingAnalysis/utils.py
qumas/MicrolensingAnalysis/windows.py
qumas/MicrolensingMaps/__init__.py
qumas/MicrolensingMaps/maps_utils.py
qumas/MicrolensingMaps/micro_maps_func.py
qumas/MicrolensingMaps/plots.py
qumas/MicrolensingTimescale/Microtimescales.py
qumas/MicrolensingTimescale/__init__.py
qumas/MicrolensingTimescale/delete_soon/scales.py
qumas/MicrolensingTimescale/delete_soon/utils.py
qumas/MicrolensingTimescale/v_cmb.py
qumas/Tables/__init__.py
qumas/Tables/filterinfo/README.md
qumas/Tables/filterinfo/filter_unique.csv
qumas/Tables/photometry/Agnello_2015MNRAS.454.1260A.csv
qumas/Tables/photometry/Agnello_2018MNRAS.474.3391A.csv
qumas-0.1.2.dist-info/LICENSE
qumas-0.1.2.dist-info/METADATA
qumas-0.1.2.dist-info/WHEEL
qumas-0.1.2.dist-info/entry_points.txt
qumas-0.1.2.dist-info/RECORD
